automation_ide/__init__.py
automation_ide/__main__.py
automation_ide/automation_editor_ui/__init__.py
automation_ide/automation_editor_ui/connect_gui/__init__.py
automation_ide/automation_editor_ui/connect_gui/ssh/__init__.py
automation_ide/automation_editor_ui/connect_gui/ssh/ssh_command_widget.py
automation_ide/automation_editor_ui/connect_gui/ssh/ssh_file_viewer_widget.py
automation_ide/automation_editor_ui/connect_gui/ssh/ssh_login_widget.py
automation_ide/automation_editor_ui/connect_gui/ssh/ssh_main_widget.py
automation_ide/automation_editor_ui/connect_gui/url/__init__.py
automation_ide/automation_editor_ui/connect_gui/url/ai_code_review_gui.py
automation_ide/automation_editor_ui/editor_main/__init__.py
automation_ide/automation_editor_ui/editor_main/main_ui.py
automation_ide/automation_editor_ui/extend_multi_language/__init__.py
automation_ide/automation_editor_ui/extend_multi_language/extend_english.py
automation_ide/automation_editor_ui/extend_multi_language/extend_traditional_chinese.py
automation_ide/automation_editor_ui/extend_multi_language/update_language_dict.py
automation_ide/automation_editor_ui/menu/__init__.py
automation_ide/automation_editor_ui/menu/build_menubar.py
automation_ide/automation_editor_ui/menu/menu_utils.py
automation_ide/automation_editor_ui/menu/automation_menu/__init__.py
automation_ide/automation_editor_ui/menu/automation_menu/api_testka_menu/__init__.py
automation_ide/automation_editor_ui/menu/automation_menu/api_testka_menu/build_api_testka_menu.py
automation_ide/automation_editor_ui/menu/automation_menu/auto_control_menu/__init__.py
automation_ide/automation_editor_ui/menu/automation_menu/auto_control_menu/build_autocontrol_menu.py
automation_ide/automation_editor_ui/menu/automation_menu/automation_file_menu/__init__.py
automation_ide/automation_editor_ui/menu/automation_menu/automation_file_menu/build_automation_file_menu.py
automation_ide/automation_editor_ui/menu/automation_menu/load_density_menu/__init__.py
automation_ide-0.0.58.dist-info/licenses/LICENSE
automation_ide-0.0.58.dist-info/METADATA
automation_ide-0.0.58.dist-info/WHEEL
automation_ide-0.0.58.dist-info/top_level.txt
automation_ide-0.0.58.dist-info/RECORD
